mnemograph/__init__.py
mnemograph/__main__.py
mnemograph/branches.py
mnemograph/cli.py
mnemograph/constants.py
mnemograph/engine.py
mnemograph/events.py
mnemograph/linearize.py
mnemograph/models.py
mnemograph/retrieval.py
mnemograph/server.py
mnemograph/similarity.py
mnemograph/state.py
mnemograph/time_travel.py
mnemograph/timeutil.py
mnemograph/vcs.py
mnemograph/vectors.py
mnemograph/weights.py
mnemograph/data/__init__.py
mnemograph/data/guide_seed.json
mnemograph/tools/__init__.py
mnemograph/viz/__init__.py
mnemograph/viz/export.py
mnemograph/viz/templates/graph.html
mnemograph-0.4.2.dist-info/METADATA
mnemograph-0.4.2.dist-info/WHEEL
mnemograph-0.4.2.dist-info/entry_points.txt
mnemograph-0.4.2.dist-info/licenses/LICENSE
mnemograph-0.4.2.dist-info/RECORD
