Metadata-Version: 2.4
Name: mnemograph
Version: 0.4.2
Summary: Event-sourced knowledge graph memory for AI coding agents (MCP server)
Project-URL: Homepage, https://github.com/tm42/mnemograph
Project-URL: Repository, https://github.com/tm42/mnemograph
License-File: LICENSE
Requires-Python: >=3.11
Requires-Dist: click>=8.0
Requires-Dist: gitpython>=3.1
Requires-Dist: mcp>=1.25.0
Requires-Dist: pydantic>=2.12.5
Requires-Dist: python-dateutil>=2.8
Requires-Dist: python-ulid>=3.1.0
Requires-Dist: rich>=13.0
Requires-Dist: sentence-transformers>=5.2.0
Requires-Dist: sqlite-vec>=0.1.6
